Dpowers/Dfuncs.py
Dpowers/__init__.py
Dpowers/autoadapt.py
Dpowers/default_backends.py
Dpowers/winapps.py
Dpowers/clipboardpower/__init__.py
Dpowers/clipboardpower/adapt_xclip_bash.py
Dpowers/clipboardpower/adapt_xsel_bash.py
Dpowers/dialogpower/__init__.py
Dpowers/dialogpower/adapt_tkinter.py
Dpowers/dialogpower/adapt_zenity_bash.py
Dpowers/editing/__init__.py
Dpowers/editing/ressource_classes.py
Dpowers/editing/imagepower/__init__.py
Dpowers/editing/imagepower/adapt_pil.py
Dpowers/editing/imagepower/adapt_wand.py
Dpowers/editing/mp3power/__init__.py
Dpowers/editing/mp3power/adapt_eyed3.py
Dpowers/events/__init__.py
Dpowers/events/event_classes.py
Dpowers/events/keybutton_classes.py
Dpowers/events/keybutton_names.py
Dpowers/events/trigman.py
Dpowers/events/waiter.py
Dpowers/events/hookpower/__init__.py
Dpowers/events/hookpower/adapt_evdev.py
Dpowers/events/hookpower/adapt_pynput.py
Dpowers/events/hookpower/baseclasses.py
Dpowers/events/sending/__init__.py
Dpowers/events/sending/event_sender.py
Dpowers/events/sending/keybpower/__init__.py
Dpowers/events/sending/keybpower/adapt_evdev.py
Dpowers/events/sending/keybpower/adapt_pynput.py
Dpowers/events/sending/keybpower/adapt_xdotool_bash.py
Dpowers/events/sending/mousepower/__init__.py
Dpowers/events/sending/mousepower/adapt_evdev.py
Dpowers/events/sending/mousepower/adapt_pynput.py
Dpowers/events/sending/senderpower/__init__.py
Dpowers/events/sending/senderpower/adapt_evdev.py
Dpowers/iconpower/__init__.py
Dpowers/iconpower/adapt_pystray.py
Dpowers/iconpower/adapt_yad_bash.py
Dpowers/iconpower/icons/Dicon.png
Dpowers/iconpower/icons/Dicon.svg
Dpowers/iconpower/icons/__init__.py
Dpowers/notificationpower/__init__.py
Dpowers/notificationpower/adapt_notify_send_bash.py
Dpowers/sound/__init__.py
Dpowers/sound/ttspower/__init__.py
Dpowers/sound/ttspower/adapt_ttsx3.py
Dpowers/windowpower/__init__.py
Dpowers/windowpower/adapt_xtools_bash.py
Dpowers/windowpower/windowobjects.py
Dpowers-0.1.6.dist-info/COPYING
Dpowers-0.1.6.dist-info/METADATA
Dpowers-0.1.6.dist-info/WHEEL
Dpowers-0.1.6.dist-info/top_level.txt
Dpowers-0.1.6.dist-info/RECORD
