Metadata-Version: 2.1
Name: Dpowers
Version: 0.1.6
Summary: Unified Interface for automatic interaction
Home-page: https://github.com/dp0s/Dpowers
Author: DPS
Author-email: dps@my.mail.de
Classifier: Programming Language :: Python :: 3
Classifier: License :: OSI Approved :: GNU General Public License v3 (GPLv3)
Requires-Python: >=3.6
License-File: COPYING
Requires-Dist: Dhelpers ==0.1.6
